opennsfw2/__init__.py
opennsfw2/_download.py
opennsfw2/_image.py
opennsfw2/_inference.py
opennsfw2/_inspection.py
opennsfw2/_model.py
opennsfw2/_typing.py
opennsfw2/py.typed
tests/__init__.py
tests/_test.py
opennsfw2-0.14.0.dist-info/LICENSE
opennsfw2-0.14.0.dist-info/METADATA
opennsfw2-0.14.0.dist-info/WHEEL
opennsfw2-0.14.0.dist-info/top_level.txt
opennsfw2-0.14.0.dist-info/RECORD
