Metadata-Version: 2.1
Name: opennsfw2
Version: 0.14.0
Summary: TensorFlow 2 implementation of the Yahoo Open-NSFW model
Home-page: https://github.com/bhky/opennsfw2
Author: attr: opennsfw2.__author__
Author-email: xtorch501@gmail.com
Classifier: Programming Language :: Python :: 3
Classifier: License :: OSI Approved :: MIT License
Classifier: Operating System :: OS Independent
Requires-Python: >=3.9
License-File: LICENSE
Requires-Dist: gdown>=4.2.0
Requires-Dist: keras>=2.14.0
Requires-Dist: matplotlib>=3.0.0
Requires-Dist: numpy>=1.22.0
Requires-Dist: opencv-python>=4.0.0.0
Requires-Dist: Pillow>=8.0.0
Requires-Dist: scikit-image>=0.18.0
Requires-Dist: tqdm>=4.62
